dccs_utils/__init__.py
dccs_utils/dccsutils.py
dccs_utils-1.0.0.dist-info/LICENSE
dccs_utils-1.0.0.dist-info/METADATA
dccs_utils-1.0.0.dist-info/WHEEL
dccs_utils-1.0.0.dist-info/entry_points.txt
dccs_utils-1.0.0.dist-info/top_level.txt
dccs_utils-1.0.0.dist-info/RECORD
