Metadata-Version: 2.1
Name: dccs-utils
Version: 1.0.0
Summary: Utility library for making HTTP requests
Home-page: https://github.com/Dccs-team/DCCSUtils
Author: Md Saimun
Author-email: teamdccs@gmail.com
Classifier: Development Status :: 5 - Production/Stable
Classifier: Intended Audience :: Developers
Classifier: License :: OSI Approved :: MIT License
Classifier: Programming Language :: Python :: 3
Classifier: Programming Language :: Python :: 3.6
Classifier: Programming Language :: Python :: 3.7
Classifier: Programming Language :: Python :: 3.8
Classifier: Programming Language :: Python :: 3.9
Requires-Python: >=3.6
License-File: LICENSE
Requires-Dist: requests
Requires-Dist: beautifulsoup4
